blackbeard2109/Data_Cleaning_librery.py
blackbeard2109/ML.py
blackbeard2109/__init__.py
blackbeard2109/visualization.py
blackbeard2109-0.2.3.dist-info/LICENSE.txt
blackbeard2109-0.2.3.dist-info/METADATA
blackbeard2109-0.2.3.dist-info/WHEEL
blackbeard2109-0.2.3.dist-info/top_level.txt
blackbeard2109-0.2.3.dist-info/RECORD
