Metadata-Version: 2.1
Name: blackbeard2109
Version: 0.2.3
Summary: This library is designed for people who need to optimize time in an agile way with an ease of understanding and could 
Home-page: https://github.com/ds2109fulltime/BLACKBEARD
Author: The Bridge Data Science Team 2109
Author-email: datascience2109thebridge@gmail.com
License: UNKNOWN
Platform: UNKNOWN
Classifier: Programming Language :: Python :: 3
Classifier: License :: OSI Approved :: MIT License
Classifier: Operating System :: OS Independent
Requires-Python: >=3.6
License-File: LICENSE.txt
Requires-Dist: pandas
Requires-Dist: numpy
Requires-Dist: opencv-python
Requires-Dist: scikit-learn
Requires-Dist: imageio
Requires-Dist: folium
Requires-Dist: plotly
Requires-Dist: scipy
Requires-Dist: IPython
Requires-Dist: matplotlib
Requires-Dist: seaborn
Requires-Dist: tensorflow
Requires-Dist: xgboost
Requires-Dist: mljar-supervised
